mdformat_myst/__init__.py
mdformat_myst/_directives.py
mdformat_myst/plugin.py
mdformat_myst/py.typed
mdformat_myst-0.2.2.dist-info/entry_points.txt
mdformat_myst-0.2.2.dist-info/licenses/LICENSE
mdformat_myst-0.2.2.dist-info/WHEEL
mdformat_myst-0.2.2.dist-info/METADATA
mdformat_myst-0.2.2.dist-info/RECORD
