Metadata-Version: 2.4
Name: mdformat_myst
Version: 0.2.2
Summary: Mdformat plugin for MyST compatibility.
Home-page: https://github.com/hukkinj1/mdformat-myst
Keywords: mdformat,markdown,formatter,gfm
Author: Taneli Hukkinen
Maintainer: Executable Book Project
Maintainer-email: executablebooks@gmail.com
Requires-Python: >=3.9
License: MIT
Classifier: Intended Audience :: Developers
Classifier: License :: OSI Approved :: MIT License
Classifier: Programming Language :: Python :: 3
Classifier: Topic :: Software Development :: Libraries :: Python Modules
License-File: LICENSE
Requires-Dist: mdformat >=0.7.0
Requires-Dist: mdit-py-plugins >=0.3.0
Requires-Dist: mdformat-tables >=0.4.0
Requires-Dist: mdformat-frontmatter >=0.3.2
Requires-Dist: mdformat-footnote >=0.1.1
Requires-Dist: ruamel.yaml >=0.16.0
Requires-Dist: pre-commit ; extra == "dev"
Requires-Dist: pytest ; extra == "test"
Requires-Dist: coverage ; extra == "test"
Requires-Dist: pytest-cov ; extra == "test"
Provides-Extra: dev
Provides-Extra: test
